odoo/addons/sms_twilio/README.rst
odoo/addons/sms_twilio/__init__.py
odoo/addons/sms_twilio/__manifest__.py
odoo/addons/sms_twilio/i18n/it.po
odoo/addons/sms_twilio/i18n/sms_twilio.pot
odoo/addons/sms_twilio/models/__init__.py
odoo/addons/sms_twilio/models/iap_account.py
odoo/addons/sms_twilio/models/sms_api.py
odoo/addons/sms_twilio/models/sms_sms.py
odoo/addons/sms_twilio/models/twilio_numbers.py
odoo/addons/sms_twilio/readme/CONFIGURE.rst
odoo/addons/sms_twilio/readme/CONTRIBUTORS.rst
odoo/addons/sms_twilio/readme/DESCRIPTION.rst
odoo/addons/sms_twilio/security/ir.model.access.csv
odoo/addons/sms_twilio/static/description/icon.png
odoo/addons/sms_twilio/static/description/index.html
odoo/addons/sms_twilio/views/iap_account_view.xml
odoo/addons/sms_twilio/views/sms_sms_view.xml
odoo_addon_sms_twilio-16.0.1.0.0.3.dist-info/METADATA
odoo_addon_sms_twilio-16.0.1.0.0.3.dist-info/WHEEL
odoo_addon_sms_twilio-16.0.1.0.0.3.dist-info/top_level.txt
odoo_addon_sms_twilio-16.0.1.0.0.3.dist-info/RECORD
